async_chat_engine/__init__.py
async_chat_engine/chat_engine.py
async_chat_engine/producer_consumer.py
async_chat_engine/utility.py
async_chat_engine-1.0.14.dist-info/LICENSE
async_chat_engine-1.0.14.dist-info/METADATA
async_chat_engine-1.0.14.dist-info/WHEEL
async_chat_engine-1.0.14.dist-info/top_level.txt
async_chat_engine-1.0.14.dist-info/RECORD
